Workbook

Sheet 使い方
A1: 見積書作成ツールの使い方
A3: 1. 「項目選択」シートで、見積書に載せたい項目の「選択」を TRUE(チェック)にする
A4: 2. 数量を必要に応じて変更する(単価・項目名の追加/変更も黄色セルで可能)
A5: 3. 「見積書」シートで宛先・件名・見積番号など黄色のセルを入力する
A6: 4. 「見積書」シートを印刷 または PDF で保存して提出する
A8: ■ ルール
A9: ・黄色のセル = 入力するセル。白いセルは計算式なので編集しないでください。
A10: ・見積書に載る明細は最大 20 行です。
A11: ・明細は「項目選択」シートの並び順で掲載されます。
A13: ■ チームでの使い方
A14: ・このファイルを SharePoint / OneDrive / Teams に置き、マスタ(原本)として管理します。
A15: ・見積書を作るときは「名前を付けて保存」でコピーしてから編集すると原本が崩れません。
A16: ・マクロ不使用のため、Excel for the web(ブラウザ)や Teams 上でもそのまま使えます。

Sheet 項目選択
A1: 見積項目の選択
A2: 「選択」列で TRUE(チェック)にした項目が「見積書」シートに自動で反映されます。黄色のセルを編集してください。
A3: ※Microsoft 365 の場合、A列を選択して［挿入］→［チェックボックス］でクリック式のチェックボックスになります。
A4: 選択 | B4: 区分 | C4: 項目名 | D4: 単位 | E4: 単価(円) | F4: 数量 | G4: 金額(円) | H4: 掲載順
A5: =FALSE() -> FALSE | B5: 基本費用 | C5: 現地調査費 | D5: 式 | E5: 30000 | F5: 1 | G5: =IF(C5="","",E5*F5) -> 30000 | H5: =IF(AND(A5=TRUE(),C5<>""),COUNTIF(A$5:A5,TRUE()),"")
A6: =FALSE() -> FALSE | B6: 基本費用 | C6: 設計・計画費 | D6: 式 | E6: 50000 | F6: 1 | G6: =IF(C6="","",E6*F6) -> 50000 | H6: =IF(AND(A6=TRUE(),C6<>""),COUNTIF(A$5:A6,TRUE()),"")
A7: =FALSE() -> FALSE | B7: 基本費用 | C7: 諸経費 | D7: 式 | E7: 20000 | F7: 1 | G7: =IF(C7="","",E7*F7) -> 20000 | H7: =IF(AND(A7=TRUE(),C7<>""),COUNTIF(A$5:A7,TRUE()),"")
A8: =FALSE() -> FALSE | B8: 作業費 | C8: 技術者作業費 | D8: 人日 | E8: 45000 | F8: 2 | G8: =IF(C8="","",E8*F8) -> 90000 | H8: =IF(AND(A8=TRUE(),C8<>""),COUNTIF(A$5:A8,TRUE()),"")
A9: =FALSE() -> FALSE | B9: 作業費 | C9: 測定作業費 | D9: 回 | E9: 25000 | F9: 1 | G9: =IF(C9="","",E9*F9) -> 25000 | H9: =IF(AND(A9=TRUE(),C9<>""),COUNTIF(A$5:A9,TRUE()),"")
A10: =FALSE() -> FALSE | B10: 作業費 | C10: 立会い費 | D10: 回 | E10: 15000 | F10: 1 | G10: =IF(C10="","",E10*F10) -> 15000 | H10: =IF(AND(A10=TRUE(),C10<>""),COUNTIF(A$5:A10,TRUE()),"")
A11: =FALSE() -> FALSE | B11: 機材費 | C11: 測定機器レンタル | D11: 日 | E11: 12000 | F11: 2 | G11: =IF(C11="","",E11*F11) -> 24000 | H11: =IF(AND(A11=TRUE(),C11<>""),COUNTIF(A$5:A11,TRUE()),"")
A12: =FALSE() -> FALSE | B12: 機材費 | C12: 消耗品 | D12: 式 | E12: 5000 | F12: 1 | G12: =IF(C12="","",E12*F12) -> 5000 | H12: =IF(AND(A12=TRUE(),C12<>""),COUNTIF(A$5:A12,TRUE()),"")
A13: =FALSE() -> FALSE | B13: 交通・出張 | C13: 交通費 | D13: 式 | E13: 10000 | F13: 1 | G13: =IF(C13="","",E13*F13) -> 10000 | H13: =IF(AND(A13=TRUE(),C13<>""),COUNTIF(A$5:A13,TRUE()),"")
A14: =FALSE() -> FALSE | B14: 交通・出張 | C14: 宿泊費 | D14: 泊 | E14: 12000 | F14: 1 | G14: =IF(C14="","",E14*F14) -> 12000 | H14: =IF(AND(A14=TRUE(),C14<>""),COUNTIF(A$5:A14,TRUE()),"")
A15: =FALSE() -> FALSE | B15: 報告 | C15: 報告書作成費 | D15: 部 | E15: 30000 | F15: 1 | G15: =IF(C15="","",E15*F15) -> 30000 | H15: =IF(AND(A15=TRUE(),C15<>""),COUNTIF(A$5:A15,TRUE()),"")
A16: =FALSE() -> FALSE | B16: 報告 | C16: 報告会実施費 | D16: 回 | E16: 20000 | F16: 1 | G16: =IF(C16="","",E16*F16) -> 20000 | H16: =IF(AND(A16=TRUE(),C16<>""),COUNTIF(A$5:A16,TRUE()),"")
A17: =FALSE() -> FALSE | G17: =IF(C17="","",E17*F17) | H17: =IF(AND(A17=TRUE(),C17<>""),COUNTIF(A$5:A17,TRUE()),"")
A18: =FALSE() -> FALSE | G18: =IF(C18="","",E18*F18) | H18: =IF(AND(A18=TRUE(),C18<>""),COUNTIF(A$5:A18,TRUE()),"")
A19: =FALSE() -> FALSE | G19: =IF(C19="","",E19*F19) | H19: =IF(AND(A19=TRUE(),C19<>""),COUNTIF(A$5:A19,TRUE()),"")
A20: =FALSE() -> FALSE | G20: =IF(C20="","",E20*F20) | H20: =IF(AND(A20=TRUE(),C20<>""),COUNTIF(A$5:A20,TRUE()),"")
A21: =FALSE() -> FALSE | G21: =IF(C21="","",E21*F21) | H21: =IF(AND(A21=TRUE(),C21<>""),COUNTIF(A$5:A21,TRUE()),"")
A22: =FALSE() -> FALSE | G22: =IF(C22="","",E22*F22) | H22: =IF(AND(A22=TRUE(),C22<>""),COUNTIF(A$5:A22,TRUE()),"")
A23: =FALSE() -> FALSE | G23: =IF(C23="","",E23*F23) | H23: =IF(AND(A23=TRUE(),C23<>""),COUNTIF(A$5:A23,TRUE()),"")
A24: =FALSE() -> FALSE | G24: =IF(C24="","",E24*F24) | H24: =IF(AND(A24=TRUE(),C24<>""),COUNTIF(A$5:A24,TRUE()),"")
A25: =FALSE() -> FALSE | G25: =IF(C25="","",E25*F25) | H25: =IF(AND(A25=TRUE(),C25<>""),COUNTIF(A$5:A25,TRUE()),"")
A26: =FALSE() -> FALSE | G26: =IF(C26="","",E26*F26) | H26: =IF(AND(A26=TRUE(),C26<>""),COUNTIF(A$5:A26,TRUE()),"")
A27: =FALSE() -> FALSE | G27: =IF(C27="","",E27*F27) | H27: =IF(AND(A27=TRUE(),C27<>""),COUNTIF(A$5:A27,TRUE()),"")
A28: =FALSE() -> FALSE | G28: =IF(C28="","",E28*F28) | H28: =IF(AND(A28=TRUE(),C28<>""),COUNTIF(A$5:A28,TRUE()),"")
... A64: =FALSE() -> FALSE | G64: =IF(C64="","",E64*F64) | H64: =IF(AND(A64=TRUE(),C64<>""),COUNTIF(A$5:A64,TRUE()),"")
F66: 選択件数 | G66: =COUNTIF(A5:A64,TRUE()) -> 0 | H66: =IF(G66>20,"⚠ 20件まで","")

Sheet 見積書
A1: 御 見 積 書
A3: 株式会社サンプル商事 | D3: 御中 | E3: 見積番号 | F3: Q-2026-001 | H3: 消費税率 | I3: 0.1
A4: 件名：測定業務一式 | E4: 見積日 | F4: =TODAY() -> 46304
E5: 有効期限 | F5: =F4+30 -> 46334
A6: 下記の通り御見積申し上げます。
E7: 〇〇株式会社
E8: 〒000-0000 東京都〇〇区〇〇 1-2-3
A9: 御見積金額(税込) | C9: =F35 -> 0 | E9: TEL 00-0000-0000
E10: 担当：〇〇
A12: No. | B12: 項目名 | C12: 数量 | D12: 単位 | E12: 単価 | F12: 金額
A13: =IF(COUNTIF(項目選択!$H$5:$H$64,1)=0,"",1) | B13: =IFERROR(INDEX(項目選択!$C$5:$C$64,MATCH(1,項目選択!$H$5:$H$64,0)),"") | C13: =IFERROR(INDEX(項目選択!$F$5:$F$64,MATCH(1,項目選択!$H$5:$H$64,0)),"") | D13: =IFERROR(INDEX(項目選択!$D$5:$D$64,MATCH(1,項目選択!$H$5:$H$64,0)),"") | E13: =IFERROR(INDEX(項目選択!$E$5:$E$64,MATCH(1,項目選択!$H$5:$H$64,0)),"") | F13: =IF(B13="","",C13*E13)
A14: =IF(COUNTIF(項目選択!$H$5:$H$64,2)=0,"",2) | B14: =IFERROR(INDEX(項目選択!$C$5:$C$64,MATCH(2,項目選択!$H$5:$H$64,0)),"") | C14: =IFERROR(INDEX(項目選択!$F$5:$F$64,MATCH(2,項目選択!$H$5:$H$64,0)),"") | D14: =IFERROR(INDEX(項目選択!$D$5:$D$64,MATCH(2,項目選択!$H$5:$H$64,0)),"") | E14: =IFERROR(INDEX(項目選択!$E$5:$E$64,MATCH(2,項目選択!$H$5:$H$64,0)),"") | F14: =IF(B14="","",C14*E14)
A15: =IF(COUNTIF(項目選択!$H$5:$H$64,3)=0,"",3) | B15: =IFERROR(INDEX(項目選択!$C$5:$C$64,MATCH(3,項目選択!$H$5:$H$64,0)),"") | C15: =IFERROR(INDEX(項目選択!$F$5:$F$64,MATCH(3,項目選択!$H$5:$H$64,0)),"") | D15: =IFERROR(INDEX(項目選択!$D$5:$D$64,MATCH(3,項目選択!$H$5:$H$64,0)),"") | E15: =IFERROR(INDEX(項目選択!$E$5:$E$64,MATCH(3,項目選択!$H$5:$H$64,0)),"") | F15: =IF(B15="","",C15*E15)
A16: =IF(COUNTIF(項目選択!$H$5:$H$64,4)=0,"",4) | B16: =IFERROR(INDEX(項目選択!$C$5:$C$64,MATCH(4,項目選択!$H$5:$H$64,0)),"") | C16: =IFERROR(INDEX(項目選択!$F$5:$F$64,MATCH(4,項目選択!$H$5:$H$64,0)),"") | D16: =IFERROR(INDEX(項目選択!$D$5:$D$64,MATCH(4,項目選択!$H$5:$H$64,0)),"") | E16: =IFERROR(INDEX(項目選択!$E$5:$E$64,MATCH(4,項目選択!$H$5:$H$64,0)),"") | F16: =IF(B16="","",C16*E16)
A17: =IF(COUNTIF(項目選択!$H$5:$H$64,5)=0,"",5) | B17: =IFERROR(INDEX(項目選択!$C$5:$C$64,MATCH(5,項目選択!$H$5:$H$64,0)),"") | C17: =IFERROR(INDEX(項目選択!$F$5:$F$64,MATCH(5,項目選択!$H$5:$H$64,0)),"") | D17: =IFERROR(INDEX(項目選択!$D$5:$D$64,MATCH(5,項目選択!$H$5:$H$64,0)),"") | E17: =IFERROR(INDEX(項目選択!$E$5:$E$64,MATCH(5,項目選択!$H$5:$H$64,0)),"") | F17: =IF(B17="","",C17*E17)
A18: =IF(COUNTIF(項目選択!$H$5:$H$64,6)=0,"",6) | B18: =IFERROR(INDEX(項目選択!$C$5:$C$64,MATCH(6,項目選択!$H$5:$H$64,0)),"") | C18: =IFERROR(INDEX(項目選択!$F$5:$F$64,MATCH(6,項目選択!$H$5:$H$64,0)),"") | D18: =IFERROR(INDEX(項目選択!$D$5:$D$64,MATCH(6,項目選択!$H$5:$H$64,0)),"") | E18: =IFERROR(INDEX(項目選択!$E$5:$E$64,MATCH(6,項目選択!$H$5:$H$64,0)),"") | F18: =IF(B18="","",C18*E18)
A19: =IF(COUNTIF(項目選択!$H$5:$H$64,7)=0,"",7) | B19: =IFERROR(INDEX(項目選択!$C$5:$C$64,MATCH(7,項目選択!$H$5:$H$64,0)),"") | C19: =IFERROR(INDEX(項目選択!$F$5:$F$64,MATCH(7,項目選択!$H$5:$H$64,0)),"") | D19: =IFERROR(INDEX(項目選択!$D$5:$D$64,MATCH(7,項目選択!$H$5:$H$64,0)),"") | E19: =IFERROR(INDEX(項目選択!$E$5:$E$64,MATCH(7,項目選択!$H$5:$H$64,0)),"") | F19: =IF(B19="","",C19*E19)
A20: =IF(COUNTIF(項目選択!$H$5:$H$64,8)=0,"",8) | B20: =IFERROR(INDEX(項目選択!$C$5:$C$64,MATCH(8,項目選択!$H$5:$H$64,0)),"") | C20: =IFERROR(INDEX(項目選択!$F$5:$F$64,MATCH(8,項目選択!$H$5:$H$64,0)),"") | D20: =IFERROR(INDEX(項目選択!$D$5:$D$64,MATCH(8,項目選択!$H$5:$H$64,0)),"") | E20: =IFERROR(INDEX(項目選択!$E$5:$E$64,MATCH(8,項目選択!$H$5:$H$64,0)),"") | F20: =IF(B20="","",C20*E20)
A21: =IF(COUNTIF(項目選択!$H$5:$H$64,9)=0,"",9) | B21: =IFERROR(INDEX(項目選択!$C$5:$C$64,MATCH(9,項目選択!$H$5:$H$64,0)),"") | C21: =IFERROR(INDEX(項目選択!$F$5:$F$64,MATCH(9,項目選択!$H$5:$H$64,0)),"") | D21: =IFERROR(INDEX(項目選択!$D$5:$D$64,MATCH(9,項目選択!$H$5:$H$64,0)),"") | E21: =IFERROR(INDEX(項目選択!$E$5:$E$64,MATCH(9,項目選択!$H$5:$H$64,0)),"") | F21: =IF(B21="","",C21*E21)
A22: =IF(COUNTIF(項目選択!$H$5:$H$64,10)=0,"",10) | B22: =IFERROR(INDEX(項目選択!$C$5:$C$64,MATCH(10,項目選択!$H$5:$H$64,0)),"") | C22: =IFERROR(INDEX(項目選択!$F$5:$F$64,MATCH(10,項目選択!$H$5:$H$64,0)),"") | D22: =IFERROR(INDEX(項目選択!$D$5:$D$64,MATCH(10,項目選択!$H$5:$H$64,0)),"") | E22: =IFERROR(INDEX(項目選択!$E$5:$E$64,MATCH(10,項目選択!$H$5:$H$64,0)),"") | F22: =IF(B22="","",C22*E22)
A23: =IF(COUNTIF(項目選択!$H$5:$H$64,11)=0,"",11) | B23: =IFERROR(INDEX(項目選択!$C$5:$C$64,MATCH(11,項目選択!$H$5:$H$64,0)),"") | C23: =IFERROR(INDEX(項目選択!$F$5:$F$64,MATCH(11,項目選択!$H$5:$H$64,0)),"") | D23: =IFERROR(INDEX(項目選択!$D$5:$D$64,MATCH(11,項目選択!$H$5:$H$64,0)),"") | E23: =IFERROR(INDEX(項目選択!$E$5:$E$64,MATCH(11,項目選択!$H$5:$H$64,0)),"") | F23: =IF(B23="","",C23*E23)
A24: =IF(COUNTIF(項目選択!$H$5:$H$64,12)=0,"",12) | B24: =IFERROR(INDEX(項目選択!$C$5:$C$64,MATCH(12,項目選択!$H$5:$H$64,0)),"") | C24: =IFERROR(INDEX(項目選択!$F$5:$F$64,MATCH(12,項目選択!$H$5:$H$64,0)),"") | D24: =IFERROR(INDEX(項目選択!$D$5:$D$64,MATCH(12,項目選択!$H$5:$H$64,0)),"") | E24: =IFERROR(INDEX(項目選択!$E$5:$E$64,MATCH(12,項目選択!$H$5:$H$64,0)),"") | F24: =IF(B24="","",C24*E24)
A25: =IF(COUNTIF(項目選択!$H$5:$H$64,13)=0,"",13) | B25: =IFERROR(INDEX(項目選択!$C$5:$C$64,MATCH(13,項目選択!$H$5:$H$64,0)),"") | C25: =IFERROR(INDEX(項目選択!$F$5:$F$64,MATCH(13,項目選択!$H$5:$H$64,0)),"") | D25: =IFERROR(INDEX(項目選択!$D$5:$D$64,MATCH(13,項目選択!$H$5:$H$64,0)),"") | E25: =IFERROR(INDEX(項目選択!$E$5:$E$64,MATCH(13,項目選択!$H$5:$H$64,0)),"") | F25: =IF(B25="","",C25*E25)
A26: =IF(COUNTIF(項目選択!$H$5:$H$64,14)=0,"",14) | B26: =IFERROR(INDEX(項目選択!$C$5:$C$64,MATCH(14,項目選択!$H$5:$H$64,0)),"") | C26: =IFERROR(INDEX(項目選択!$F$5:$F$64,MATCH(14,項目選択!$H$5:$H$64,0)),"") | D26: =IFERROR(INDEX(項目選択!$D$5:$D$64,MATCH(14,項目選択!$H$5:$H$64,0)),"") | E26: =IFERROR(INDEX(項目選択!$E$5:$E$64,MATCH(14,項目選択!$H$5:$H$64,0)),"") | F26: =IF(B26="","",C26*E26)
A27: =IF(COUNTIF(項目選択!$H$5:$H$64,15)=0,"",15) | B27: =IFERROR(INDEX(項目選択!$C$5:$C$64,MATCH(15,項目選択!$H$5:$H$64,0)),"") | C27: =IFERROR(INDEX(項目選択!$F$5:$F$64,MATCH(15,項目選択!$H$5:$H$64,0)),"") | D27: =IFERROR(INDEX(項目選択!$D$5:$D$64,MATCH(15,項目選択!$H$5:$H$64,0)),"") | E27: =IFERROR(INDEX(項目選択!$E$5:$E$64,MATCH(15,項目選択!$H$5:$H$64,0)),"") | F27: =IF(B27="","",C27*E27)
A28: =IF(COUNTIF(項目選択!$H$5:$H$64,16)=0,"",16) | B28: =IFERROR(INDEX(項目選択!$C$5:$C$64,MATCH(16,項目選択!$H$5:$H$64,0)),"") | C28: =IFERROR(INDEX(項目選択!$F$5:$F$64,MATCH(16,項目選択!$H$5:$H$64,0)),"") | D28: =IFERROR(INDEX(項目選択!$D$5:$D$64,MATCH(16,項目選択!$H$5:$H$64,0)),"") | E28: =IFERROR(INDEX(項目選択!$E$5:$E$64,MATCH(16,項目選択!$H$5:$H$64,0)),"") | F28: =IF(B28="","",C28*E28)
A29: =IF(COUNTIF(項目選択!$H$5:$H$64,17)=0,"",17) | B29: =IFERROR(INDEX(項目選択!$C$5:$C$64,MATCH(17,項目選択!$H$5:$H$64,0)),"") | C29: =IFERROR(INDEX(項目選択!$F$5:$F$64,MATCH(17,項目選択!$H$5:$H$64,0)),"") | D29: =IFERROR(INDEX(項目選択!$D$5:$D$64,MATCH(17,項目選択!$H$5:$H$64,0)),"") | E29: =IFERROR(INDEX(項目選択!$E$5:$E$64,MATCH(17,項目選択!$H$5:$H$64,0)),"") | F29: =IF(B29="","",C29*E29)
A30: =IF(COUNTIF(項目選択!$H$5:$H$64,18)=0,"",18) | B30: =IFERROR(INDEX(項目選択!$C$5:$C$64,MATCH(18,項目選択!$H$5:$H$64,0)),"") | C30: =IFERROR(INDEX(項目選択!$F$5:$F$64,MATCH(18,項目選択!$H$5:$H$64,0)),"") | D30: =IFERROR(INDEX(項目選択!$D$5:$D$64,MATCH(18,項目選択!$H$5:$H$64,0)),"") | E30: =IFERROR(INDEX(項目選択!$E$5:$E$64,MATCH(18,項目選択!$H$5:$H$64,0)),"") | F30: =IF(B30="","",C30*E30)
A31: =IF(COUNTIF(項目選択!$H$5:$H$64,19)=0,"",19) | B31: =IFERROR(INDEX(項目選択!$C$5:$C$64,MATCH(19,項目選択!$H$5:$H$64,0)),"") | C31: =IFERROR(INDEX(項目選択!$F$5:$F$64,MATCH(19,項目選択!$H$5:$H$64,0)),"") | D31: =IFERROR(INDEX(項目選択!$D$5:$D$64,MATCH(19,項目選択!$H$5:$H$64,0)),"") | E31: =IFERROR(INDEX(項目選択!$E$5:$E$64,MATCH(19,項目選択!$H$5:$H$64,0)),"") | F31: =IF(B31="","",C31*E31)
A32: =IF(COUNTIF(項目選択!$H$5:$H$64,20)=0,"",20) | B32: =IFERROR(INDEX(項目選択!$C$5:$C$64,MATCH(20,項目選択!$H$5:$H$64,0)),"") | C32: =IFERROR(INDEX(項目選択!$F$5:$F$64,MATCH(20,項目選択!$H$5:$H$64,0)),"") | D32: =IFERROR(INDEX(項目選択!$D$5:$D$64,MATCH(20,項目選択!$H$5:$H$64,0)),"") | E32: =IFERROR(INDEX(項目選択!$E$5:$E$64,MATCH(20,項目選択!$H$5:$H$64,0)),"") | F32: =IF(B32="","",C32*E32)
D33: 小計 | F33: =SUM(F13:F32) -> 0
D34: 消費税 | F34: =ROUNDDOWN(F33*$I$3,0) -> 0
D35: 合計 | F35: =F33+F34 -> 0
A37: 備考
A38: ・お支払条件：月末締め翌月末払い
